bento2seldon4recsys/__init__.py
bento2seldon4recsys/bento.py
bento2seldon4recsys/model.py
bento2seldon4recsys/monitoring.py
bento2seldon4recsys/py.typed
bento2seldon4recsys/ranking_metrics.py
bento2seldon4recsys/router/__init__.py
bento2seldon4recsys/router/ab_test/__init__.py
bento2seldon4recsys/router/ab_test/model.py
bento2seldon4recsys-0.1.3.dist-info/LICENSE
bento2seldon4recsys-0.1.3.dist-info/WHEEL
bento2seldon4recsys-0.1.3.dist-info/METADATA
bento2seldon4recsys-0.1.3.dist-info/RECORD
