Metadata-Version: 2.1
Name: bento2seldon4recsys
Version: 0.1.3
Summary: Extension of bento2seldon for RecSys.
Home-page: https://github.com/deeplearningbrasil/bento2seldon4recsys
License: Apache Software License 2.0
Keywords: machine learning,deployment,recsys
Author: fernandocamargoai
Author-email: fernando.camargo.ai@gmail.com
Requires-Python: >=3.7,<4.0
Classifier: Development Status :: 3 - Alpha
Classifier: Intended Audience :: Developers
Classifier: License :: Other/Proprietary License
Classifier: Operating System :: OS Independent
Classifier: Programming Language :: Python :: 3
Classifier: Programming Language :: Python :: 3.10
Classifier: Programming Language :: Python :: 3.7
Classifier: Programming Language :: Python :: 3.8
Classifier: Programming Language :: Python :: 3.9
Classifier: Topic :: Scientific/Engineering :: Artificial Intelligence
Classifier: Topic :: Software Development :: Libraries :: Python Modules
Requires-Dist: bento2seldon (>=0.4.0)
Requires-Dist: importlib_metadata (>=4.5.0,<5.0.0); python_version < "3.8"
Requires-Dist: pandas (>=0.23)
Requires-Dist: scikit-learn (>=0.18)
Project-URL: Repository, https://github.com/deeplearningbrasil/bento2seldon4recsys
